{
  "actual_time": 1647968421,
  "alliances": {
    "blue": {
      "dq_team_keys": [],
      "score": 32,
      "surrogate_team_keys": [],
      "team_keys": [
        "frc6300",
        "frc6024",
        "frc8267"
      ]
    },
    "red": {
      "dq_team_keys": [],
      "score": 52,
      "surrogate_team_keys": [],
      "team_keys": [
        "frc569",
        "frc6806",
        "frc1468"
      ]
    }
  },
  "comp_level": "qm",
  "event_key": "2022nyli",
  "key": "2022nyli_qm18",
  "match_number": 18,
  "post_result_time": 1647968759,
  "predicted_time": 1647968641,
  "score_breakdown": {
    "blue": {
      "adjustPoints": 0,
      "autoCargoLowerBlue": 0,
      "autoCargoLowerFar": 0,
      "autoCargoLowerNear": 2,
      "autoCargoLowerRed": 0,
      "autoCargoPoints": 4,
      "autoCargoTotal": 2,
      "autoCargoUpperBlue": 0,
      "autoCargoUpperFar": 0,
      "autoCargoUpperNear": 0,
      "autoCargoUpperRed": 0,
      "autoPoints": 8,
      "autoTaxiPoints": 4,
      "cargoBonusRankingPoint": false,
      "endgamePoints": 12,
      "endgameRobot1": "Mid",
      "endgameRobot2": "None",
      "endgameRobot3": "Mid",
      "foulCount": 0,
      "foulPoints": 0,
      "hangarBonusRankingPoint": false,
      "matchCargoTotal": 12,
      "quintetAchieved": false,
      "rp": 0,
      "taxiRobot1": "Yes",
      "taxiRobot2": "No",
      "taxiRobot3": "Yes",
      "techFoulCount": 0,
      "teleopCargoLowerBlue": 4,
      "teleopCargoLowerFar": 0,
      "teleopCargoLowerNear": 3,
      "teleopCargoLowerRed": 1,
      "teleopCargoPoints": 12,
      "teleopCargoTotal": 10,
      "teleopCargoUpperBlue": 0,
      "teleopCargoUpperFar": 0,
      "teleopCargoUpperNear": 2,
      "teleopCargoUpperRed": 0,
      "teleopPoints": 24,
      "totalPoints": 32
    },
    "red": {
      "adjustPoints": 0,
      "autoCargoLowerBlue": 0,
      "autoCargoLowerFar": 1,
      "autoCargoLowerNear": 1,
      "autoCargoLowerRed": 1,
      "autoCargoPoints": 14,
      "autoCargoTotal": 5,
      "autoCargoUpperBlue": 1,
      "autoCargoUpperFar": 0,
      "autoCargoUpperNear": 1,
      "autoCargoUpperRed": 0,
      "autoPoints": 20,
      "autoTaxiPoints": 6,
      "cargoBonusRankingPoint": true,
      "endgamePoints": 16,
      "endgameRobot1": "Mid",
      "endgameRobot2": "Mid",
      "endgameRobot3": "Low",
      "foulCount": 0,
      "foulPoints": 0,
      "hangarBonusRankingPoint": true,
      "matchCargoTotal": 20,
      "quintetAchieved": true,
      "rp": 4,
      "taxiRobot1": "Yes",
      "taxiRobot2": "Yes",
      "taxiRobot3": "Yes",
      "techFoulCount": 0,
      "teleopCargoLowerBlue": 1,
      "teleopCargoLowerFar": 2,
      "teleopCargoLowerNear": 6,
      "teleopCargoLowerRed": 5,
      "teleopCargoPoints": 16,
      "teleopCargoTotal": 15,
      "teleopCargoUpperBlue": 0,
      "teleopCargoUpperFar": 0,
      "teleopCargoUpperNear": 1,
      "teleopCargoUpperRed": 0,
      "teleopPoints": 32,
      "totalPoints": 52
    }
  },
  "set_number": 1,
  "time": 1647968100,
  "videos": [
    {
      "key": "EqbJW2E03m0",
      "type": "youtube"
    }
  ],
  "winning_alliance": "red"
}