{
  "actual_time": null,
  "alliances": {
    "blue": {
      "dq_team_keys": [],
      "score": 10,
      "surrogate_team_keys": [],
      "team_keys": [
        "frc2591",
        "frc2145",
        "frc217"
      ]
    },
    "red": {
      "dq_team_keys": [],
      "score": 6,
      "surrogate_team_keys": [],
      "team_keys": [
        "frc226",
        "frc2673",
        "frc815"
      ]
    }
  },
  "comp_level": "qm",
  "event_key": "2010oc",
  "key": "2010oc_qm74",
  "match_number": 74,
  "post_result_time": null,
  "predicted_time": null,
  "score_breakdown": null,
  "set_number": 1,
  "time": null,
  "videos": [],
  "winning_alliance": "blue"
}