{
  "actual_time": 1772815736,
  "alliances": {
    "blue": {
      "dq_team_keys": [],
      "score": 52,
      "surrogate_team_keys": [],
      "team_keys": [
        "frc8041",
        "frc245",
        "frc11386"
      ]
    },
    "red": {
      "dq_team_keys": [],
      "score": 97,
      "surrogate_team_keys": [],
      "team_keys": [
        "frc5152",
        "frc5676",
        "frc5248"
      ]
    }
  },
  "comp_level": "qm",
  "event_key": "2026milak",
  "key": "2026milak_qm4",
  "match_number": 4,
  "post_result_time": 1772815955,
  "predicted_time": 1772815553,
  "score_breakdown": {
    "blue": {
      "adjustPoints": 0,
      "autoTowerPoints": 0,
      "autoTowerRobot1": "None",
      "autoTowerRobot2": "None",
      "autoTowerRobot3": "None",
      "endGameTowerPoints": 0,
      "endGameTowerRobot1": "None",
      "endGameTowerRobot2": "None",
      "endGameTowerRobot3": "None",
      "energizedAchieved": false,
      "foulPoints": 0,
      "g206Penalty": false,
      "hubScore": {
        "autoCount": 31,
        "autoPoints": 31,
        "endgameCount": 2,
        "endgamePoints": 2,
        "shift1Count": 0,
        "shift1Points": 0,
        "shift2Count": 5,
        "shift2Points": 5,
        "shift3Count": 0,
        "shift3Points": 0,
        "shift4Count": 14,
        "shift4Points": 14,
        "teleopCount": 21,
        "teleopPoints": 21,
        "totalCount": 52,
        "totalPoints": 52,
        "transitionCount": 0,
        "transitionPoints": 0,
        "uncounted": 1
      },
      "majorFoulCount": 0,
      "minorFoulCount": 0,
      "penalties": "None",
      "rp": 0,
      "superchargedAchieved": false,
      "totalAutoPoints": 31,
      "totalPoints": 52,
      "totalTeleopPoints": 21,
      "totalTowerPoints": 0,
      "traversalAchieved": false
    },
    "red": {
      "adjustPoints": 0,
      "autoTowerPoints": 0,
      "autoTowerRobot1": "None",
      "autoTowerRobot2": "None",
      "autoTowerRobot3": "None",
      "endGameTowerPoints": 10,
      "endGameTowerRobot1": "Level1",
      "endGameTowerRobot2": "None",
      "endGameTowerRobot3": "None",
      "energizedAchieved": false,
      "foulPoints": 0,
      "g206Penalty": false,
      "hubScore": {
        "autoCount": 13,
        "autoPoints": 13,
        "endgameCount": 27,
        "endgamePoints": 27,
        "shift1Count": 24,
        "shift1Points": 24,
        "shift2Count": 0,
        "shift2Points": 0,
        "shift3Count": 20,
        "shift3Points": 20,
        "shift4Count": 0,
        "shift4Points": 0,
        "teleopCount": 74,
        "teleopPoints": 74,
        "totalCount": 87,
        "totalPoints": 87,
        "transitionCount": 3,
        "transitionPoints": 3,
        "uncounted": 14
      },
      "majorFoulCount": 0,
      "minorFoulCount": 0,
      "penalties": "None",
      "rp": 3,
      "superchargedAchieved": false,
      "totalAutoPoints": 13,
      "totalPoints": 97,
      "totalTeleopPoints": 84,
      "totalTowerPoints": 10,
      "traversalAchieved": false
    }
  },
  "set_number": 1,
  "time": 1772814240,
  "videos": [
    {
      "key": "0sNKk8WaV4I",
      "type": "youtube"
    }
  ],
  "winning_alliance": "red"
}