{
  "actual_time": 1490477330,
  "alliances": {
    "blue": {
      "dq_team_keys": [],
      "score": 262,
      "surrogate_team_keys": [],
      "team_keys": [
        "frc1806",
        "frc6026",
        "frc932"
      ]
    },
    "red": {
      "dq_team_keys": [],
      "score": 240,
      "surrogate_team_keys": [],
      "team_keys": [
        "frc4005",
        "frc3931",
        "frc2359"
      ]
    }
  },
  "comp_level": "f",
  "event_key": "2017okok",
  "key": "2017okok_f1m2",
  "match_number": 2,
  "post_result_time": 1490477556,
  "predicted_time": 1490477401,
  "score_breakdown": {
    "blue": {
      "adjustPoints": 0,
      "autoFuelHigh": 7,
      "autoFuelLow": 0,
      "autoFuelPoints": 7,
      "autoMobilityPoints": 15,
      "autoPoints": 82,
      "autoRotorPoints": 60,
      "foulCount": 0,
      "foulPoints": 0,
      "kPaBonusPoints": 0,
      "kPaRankingPointAchieved": false,
      "robot1Auto": "Mobility",
      "robot2Auto": "Mobility",
      "robot3Auto": "Mobility",
      "rotor1Auto": true,
      "rotor1Engaged": true,
      "rotor2Auto": false,
      "rotor2Engaged": true,
      "rotor3Engaged": true,
      "rotor4Engaged": false,
      "rotorBonusPoints": 0,
      "rotorRankingPointAchieved": false,
      "tba_rpEarned": null,
      "techFoulCount": 0,
      "teleopFuelHigh": 0,
      "teleopFuelLow": 0,
      "teleopFuelPoints": 0,
      "teleopPoints": 180,
      "teleopRotorPoints": 80,
      "teleopTakeoffPoints": 100,
      "totalPoints": 262,
      "touchpadFar": "ReadyForTakeoff",
      "touchpadMiddle": "ReadyForTakeoff",
      "touchpadNear": "None"
    },
    "red": {
      "adjustPoints": 0,
      "autoFuelHigh": 5,
      "autoFuelLow": 0,
      "autoFuelPoints": 5,
      "autoMobilityPoints": 15,
      "autoPoints": 20,
      "autoRotorPoints": 0,
      "foulCount": 0,
      "foulPoints": 0,
      "kPaBonusPoints": 0,
      "kPaRankingPointAchieved": false,
      "robot1Auto": "Mobility",
      "robot2Auto": "Mobility",
      "robot3Auto": "Mobility",
      "rotor1Auto": false,
      "rotor1Engaged": true,
      "rotor2Auto": false,
      "rotor2Engaged": true,
      "rotor3Engaged": true,
      "rotor4Engaged": false,
      "rotorBonusPoints": 0,
      "rotorRankingPointAchieved": false,
      "tba_rpEarned": null,
      "techFoulCount": 0,
      "teleopFuelHigh": 1,
      "teleopFuelLow": 0,
      "teleopFuelPoints": 0,
      "teleopPoints": 220,
      "teleopRotorPoints": 120,
      "teleopTakeoffPoints": 100,
      "totalPoints": 240,
      "touchpadFar": "ReadyForTakeoff",
      "touchpadMiddle": "None",
      "touchpadNear": "ReadyForTakeoff"
    }
  },
  "set_number": 1,
  "time": 1490476380,
  "videos": [
    {
      "key": "Ooqek5rDGeA",
      "type": "youtube"
    }
  ],
  "winning_alliance": "blue"
}