{
  "actual_time": 1650050110,
  "alliances": {
    "blue": {
      "dq_team_keys": [],
      "score": 76,
      "surrogate_team_keys": [],
      "team_keys": [
        "frc829",
        "frc5010",
        "frc4272"
      ]
    },
    "red": {
      "dq_team_keys": [],
      "score": 71,
      "surrogate_team_keys": [],
      "team_keys": [
        "frc868",
        "frc4926",
        "frc1018"
      ]
    }
  },
  "comp_level": "qm",
  "event_key": "2022incmp",
  "key": "2022incmp_qm24",
  "match_number": 24,
  "post_result_time": 1650050281,
  "predicted_time": 1650050239,
  "score_breakdown": {
    "blue": {
      "adjustPoints": 0,
      "autoCargoLowerBlue": 0,
      "autoCargoLowerFar": 0,
      "autoCargoLowerNear": 0,
      "autoCargoLowerRed": 0,
      "autoCargoPoints": 16,
      "autoCargoTotal": 4,
      "autoCargoUpperBlue": 1,
      "autoCargoUpperFar": 1,
      "autoCargoUpperNear": 0,
      "autoCargoUpperRed": 2,
      "autoPoints": 20,
      "autoTaxiPoints": 4,
      "cargoBonusRankingPoint": true,
      "endgamePoints": 15,
      "endgameRobot1": "Traversal",
      "endgameRobot2": "None",
      "endgameRobot3": "None",
      "foulCount": 0,
      "foulPoints": 8,
      "hangarBonusRankingPoint": false,
      "matchCargoTotal": 21,
      "quintetAchieved": false,
      "rp": 3,
      "taxiRobot1": "Yes",
      "taxiRobot2": "No",
      "taxiRobot3": "Yes",
      "techFoulCount": 0,
      "teleopCargoLowerBlue": 0,
      "teleopCargoLowerFar": 0,
      "teleopCargoLowerNear": 0,
      "teleopCargoLowerRed": 1,
      "teleopCargoPoints": 33,
      "teleopCargoTotal": 17,
      "teleopCargoUpperBlue": 4,
      "teleopCargoUpperFar": 4,
      "teleopCargoUpperNear": 5,
      "teleopCargoUpperRed": 3,
      "teleopPoints": 48,
      "totalPoints": 76
    },
    "red": {
      "adjustPoints": 0,
      "autoCargoLowerBlue": 0,
      "autoCargoLowerFar": 0,
      "autoCargoLowerNear": 1,
      "autoCargoLowerRed": 0,
      "autoCargoPoints": 14,
      "autoCargoTotal": 4,
      "autoCargoUpperBlue": 1,
      "autoCargoUpperFar": 1,
      "autoCargoUpperNear": 0,
      "autoCargoUpperRed": 1,
      "autoPoints": 18,
      "autoTaxiPoints": 4,
      "cargoBonusRankingPoint": true,
      "endgamePoints": 31,
      "endgameRobot1": "High",
      "endgameRobot2": "Traversal",
      "endgameRobot3": "Mid",
      "foulCount": 2,
      "foulPoints": 0,
      "hangarBonusRankingPoint": true,
      "matchCargoTotal": 20,
      "quintetAchieved": false,
      "rp": 2,
      "taxiRobot1": "No",
      "taxiRobot2": "Yes",
      "taxiRobot3": "Yes",
      "techFoulCount": 0,
      "teleopCargoLowerBlue": 3,
      "teleopCargoLowerFar": 2,
      "teleopCargoLowerNear": 2,
      "teleopCargoLowerRed": 3,
      "teleopCargoPoints": 22,
      "teleopCargoTotal": 16,
      "teleopCargoUpperBlue": 2,
      "teleopCargoUpperFar": 2,
      "teleopCargoUpperNear": 1,
      "teleopCargoUpperRed": 1,
      "teleopPoints": 53,
      "totalPoints": 71
    }
  },
  "set_number": 1,
  "time": 1650049440,
  "videos": [
    {
      "key": "IRscDfJn8XM",
      "type": "youtube"
    }
  ],
  "winning_alliance": "blue"
}