{
  "actual_time": null,
  "alliances": {
    "blue": {
      "dq_team_keys": [],
      "score": 61,
      "surrogate_team_keys": [],
      "team_keys": [
        "frc195",
        "frc245",
        "frc1736"
      ]
    },
    "red": {
      "dq_team_keys": [],
      "score": 37,
      "surrogate_team_keys": [],
      "team_keys": [
        "frc956",
        "frc2557",
        "frc190"
      ]
    }
  },
  "comp_level": "qm",
  "event_key": "2012arc",
  "key": "2012arc_qm75",
  "match_number": 75,
  "post_result_time": null,
  "predicted_time": null,
  "score_breakdown": null,
  "set_number": 1,
  "time": null,
  "videos": [
    {
      "key": "7Z2DqZRXw6o?t=2410",
      "type": "youtube"
    }
  ],
  "winning_alliance": "blue"
}