{
  "actual_time": 1554508643,
  "alliances": {
    "blue": {
      "dq_team_keys": [],
      "score": 71,
      "surrogate_team_keys": [],
      "team_keys": [
        "frc6417",
        "frc3476",
        "frc5869"
      ]
    },
    "red": {
      "dq_team_keys": [],
      "score": 73,
      "surrogate_team_keys": [],
      "team_keys": [
        "frc2073",
        "frc5124",
        "frc399"
      ]
    }
  },
  "comp_level": "qm",
  "event_key": "2019caav",
  "key": "2019caav_qm47",
  "match_number": 47,
  "post_result_time": 1554508865,
  "predicted_time": 1554508710,
  "score_breakdown": {
    "blue": {
      "adjustPoints": 0,
      "autoPoints": 9,
      "bay1": "Panel",
      "bay2": "PanelAndCargo",
      "bay3": "Panel",
      "bay4": "PanelAndCargo",
      "bay5": "PanelAndCargo",
      "bay6": "PanelAndCargo",
      "bay7": "PanelAndCargo",
      "bay8": "PanelAndCargo",
      "cargoPoints": 24,
      "completeRocketRankingPoint": false,
      "completedRocketFar": false,
      "completedRocketNear": false,
      "endgameRobot1": "None",
      "endgameRobot2": "HabLevel3",
      "endgameRobot3": "HabLevel1",
      "foulCount": 0,
      "foulPoints": 9,
      "habClimbPoints": 15,
      "habDockingRankingPoint": true,
      "habLineRobot1": "CrossedHabLineInSandstorm",
      "habLineRobot2": "CrossedHabLineInSandstorm",
      "habLineRobot3": "CrossedHabLineInSandstorm",
      "hatchPanelPoints": 14,
      "lowLeftRocketFar": "None",
      "lowLeftRocketNear": "Panel",
      "lowRightRocketFar": "None",
      "lowRightRocketNear": "Panel",
      "midLeftRocketFar": "None",
      "midLeftRocketNear": "PanelAndCargo",
      "midRightRocketFar": "None",
      "midRightRocketNear": "PanelAndCargo",
      "preMatchBay1": "Panel",
      "preMatchBay2": "Panel",
      "preMatchBay3": "Panel",
      "preMatchBay6": "Panel",
      "preMatchBay7": "Panel",
      "preMatchBay8": "Panel",
      "preMatchLevelRobot1": "HabLevel1",
      "preMatchLevelRobot2": "HabLevel1",
      "preMatchLevelRobot3": "HabLevel1",
      "rp": 1,
      "sandStormBonusPoints": 9,
      "techFoulCount": 0,
      "teleopPoints": 53,
      "topLeftRocketFar": "None",
      "topLeftRocketNear": "Panel",
      "topRightRocketFar": "None",
      "topRightRocketNear": "None",
      "totalPoints": 71
    },
    "red": {
      "adjustPoints": 0,
      "autoPoints": 15,
      "bay1": "PanelAndCargo",
      "bay2": "Panel",
      "bay3": "Panel",
      "bay4": "None",
      "bay5": "None",
      "bay6": "PanelAndCargo",
      "bay7": "PanelAndCargo",
      "bay8": "PanelAndCargo",
      "cargoPoints": 30,
      "completeRocketRankingPoint": false,
      "completedRocketFar": false,
      "completedRocketNear": false,
      "endgameRobot1": "HabLevel3",
      "endgameRobot2": "None",
      "endgameRobot3": "None",
      "foulCount": 3,
      "foulPoints": 0,
      "habClimbPoints": 12,
      "habDockingRankingPoint": false,
      "habLineRobot1": "CrossedHabLineInSandstorm",
      "habLineRobot2": "CrossedHabLineInSandstorm",
      "habLineRobot3": "CrossedHabLineInSandstorm",
      "hatchPanelPoints": 16,
      "lowLeftRocketFar": "PanelAndCargo",
      "lowLeftRocketNear": "Panel",
      "lowRightRocketFar": "Panel",
      "lowRightRocketNear": "PanelAndCargo",
      "midLeftRocketFar": "None",
      "midLeftRocketNear": "PanelAndCargo",
      "midRightRocketFar": "None",
      "midRightRocketNear": "PanelAndCargo",
      "preMatchBay1": "Panel",
      "preMatchBay2": "Panel",
      "preMatchBay3": "Panel",
      "preMatchBay6": "Panel",
      "preMatchBay7": "Panel",
      "preMatchBay8": "Panel",
      "preMatchLevelRobot1": "HabLevel1",
      "preMatchLevelRobot2": "HabLevel2",
      "preMatchLevelRobot3": "HabLevel2",
      "rp": 2,
      "sandStormBonusPoints": 15,
      "techFoulCount": 0,
      "teleopPoints": 58,
      "topLeftRocketFar": "None",
      "topLeftRocketNear": "PanelAndCargo",
      "topRightRocketFar": "None",
      "topRightRocketNear": "PanelAndCargo",
      "totalPoints": 73
    }
  },
  "set_number": 1,
  "time": 1554507720,
  "videos": [
    {
      "key": "y9I3PpHqfpc",
      "type": "youtube"
    }
  ],
  "winning_alliance": "red"
}