{
  "actual_time": null,
  "alliances": {
    "blue": {
      "dq_team_keys": [],
      "score": 102,
      "surrogate_team_keys": [
        "frc2506"
      ],
      "team_keys": [
        "frc2506",
        "frc1268",
        "frc2970"
      ]
    },
    "red": {
      "dq_team_keys": [],
      "score": 54,
      "surrogate_team_keys": [
        "frc2538"
      ],
      "team_keys": [
        "frc2538",
        "frc2202",
        "frc2547"
      ]
    }
  },
  "comp_level": "qm",
  "event_key": "2009wi",
  "key": "2009wi_qm19",
  "match_number": 19,
  "post_result_time": null,
  "predicted_time": null,
  "score_breakdown": null,
  "set_number": 1,
  "time": null,
  "videos": [
    {
      "key": "w8N8ttT0hcs",
      "type": "youtube"
    },
    {
      "key": "http://videos.thebluealliance.net/2009wi/2009wi_qm19.mp4",
      "type": "tba"
    }
  ],
  "winning_alliance": "blue"
}