{
  "actual_time": null,
  "alliances": {
    "blue": {
      "dq_team_keys": [],
      "score": 59,
      "surrogate_team_keys": [],
      "team_keys": [
        "frc2733",
        "frc7034B",
        "frc7034C"
      ]
    },
    "red": {
      "dq_team_keys": [],
      "score": 75,
      "surrogate_team_keys": [],
      "team_keys": [
        "frc1540L",
        "frc1540S",
        "frc3674"
      ]
    }
  },
  "comp_level": "qm",
  "event_key": "2022orbb",
  "key": "2022orbb_qm13",
  "match_number": 13,
  "post_result_time": null,
  "predicted_time": null,
  "score_breakdown": {
    "blue": {},
    "red": {}
  },
  "set_number": 1,
  "time": 1671311100,
  "videos": [],
  "winning_alliance": "red"
}