{
  "actual_time": null,
  "alliances": {
    "blue": {
      "dq_team_keys": [],
      "score": 7,
      "surrogate_team_keys": [],
      "team_keys": [
        "frc1208",
        "frc2669",
        "frc226"
      ]
    },
    "red": {
      "dq_team_keys": [],
      "score": 2,
      "surrogate_team_keys": [],
      "team_keys": [
        "frc461",
        "frc125",
        "frc801"
      ]
    }
  },
  "comp_level": "qm",
  "event_key": "2010new",
  "key": "2010new_qm3",
  "match_number": 3,
  "post_result_time": null,
  "predicted_time": null,
  "score_breakdown": null,
  "set_number": 1,
  "time": null,
  "videos": [],
  "winning_alliance": "blue"
}