{
  "actual_time": 1521231481,
  "alliances": {
    "blue": {
      "dq_team_keys": [],
      "score": 338,
      "surrogate_team_keys": [],
      "team_keys": [
        "frc5204",
        "frc4855",
        "frc5161"
      ]
    },
    "red": {
      "dq_team_keys": [],
      "score": 344,
      "surrogate_team_keys": [],
      "team_keys": [
        "frc6090",
        "frc6092",
        "frc4381"
      ]
    }
  },
  "comp_level": "qm",
  "event_key": "2018migul",
  "key": "2018migul_qm31",
  "match_number": 31,
  "post_result_time": 1521231677,
  "predicted_time": 1521231486,
  "score_breakdown": {
    "blue": {
      "adjustPoints": 0,
      "autoOwnershipPoints": 12,
      "autoPoints": 27,
      "autoQuestRankingPoint": true,
      "autoRobot1": "AutoRun",
      "autoRobot2": "AutoRun",
      "autoRobot3": "AutoRun",
      "autoRunPoints": 15,
      "autoScaleOwnershipSec": 0,
      "autoSwitchAtZero": true,
      "autoSwitchOwnershipSec": 6,
      "endgamePoints": 65,
      "endgameRobot1": "Parking",
      "endgameRobot2": "Climbing",
      "endgameRobot3": "Levitate",
      "faceTheBossRankingPoint": false,
      "foulCount": 0,
      "foulPoints": 25,
      "rp": 1,
      "tba_gameData": "RRR",
      "techFoulCount": 1,
      "teleopOwnershipPoints": 201,
      "teleopPoints": 286,
      "teleopScaleBoostSec": 0,
      "teleopScaleForceSec": 0,
      "teleopScaleOwnershipSec": 55,
      "teleopSwitchBoostSec": 10,
      "teleopSwitchForceSec": 0,
      "teleopSwitchOwnershipSec": 136,
      "totalPoints": 338,
      "vaultBoostPlayed": 1,
      "vaultBoostTotal": 1,
      "vaultForcePlayed": 0,
      "vaultForceTotal": 0,
      "vaultLevitatePlayed": 3,
      "vaultLevitateTotal": 3,
      "vaultPoints": 20
    },
    "red": {
      "adjustPoints": 0,
      "autoOwnershipPoints": 20,
      "autoPoints": 35,
      "autoQuestRankingPoint": true,
      "autoRobot1": "AutoRun",
      "autoRobot2": "AutoRun",
      "autoRobot3": "AutoRun",
      "autoRunPoints": 15,
      "autoScaleOwnershipSec": 1,
      "autoSwitchAtZero": true,
      "autoSwitchOwnershipSec": 9,
      "endgamePoints": 60,
      "endgameRobot1": "Climbing",
      "endgameRobot2": "Levitate",
      "endgameRobot3": "None",
      "faceTheBossRankingPoint": false,
      "foulCount": 0,
      "foulPoints": 25,
      "rp": 3,
      "tba_gameData": "RRR",
      "techFoulCount": 1,
      "teleopOwnershipPoints": 189,
      "teleopPoints": 284,
      "teleopScaleBoostSec": 0,
      "teleopScaleForceSec": 0,
      "teleopScaleOwnershipSec": 77,
      "teleopSwitchBoostSec": 0,
      "teleopSwitchForceSec": 7,
      "teleopSwitchOwnershipSec": 112,
      "totalPoints": 344,
      "vaultBoostPlayed": 0,
      "vaultBoostTotal": 3,
      "vaultForcePlayed": 1,
      "vaultForceTotal": 1,
      "vaultLevitatePlayed": 3,
      "vaultLevitateTotal": 3,
      "vaultPoints": 35
    }
  },
  "set_number": 1,
  "time": 1521230400,
  "videos": [
    {
      "key": "GZWOx1kl0v4",
      "type": "youtube"
    }
  ],
  "winning_alliance": "red"
}