{
  "actual_time": 1680885642,
  "alliances": {
    "blue": {
      "dq_team_keys": [],
      "score": 39,
      "surrogate_team_keys": [],
      "team_keys": [
        "frc1750",
        "frc8064",
        "frc9244"
      ]
    },
    "red": {
      "dq_team_keys": [],
      "score": 82,
      "surrogate_team_keys": [],
      "team_keys": [
        "frc9007",
        "frc3163",
        "frc6832"
      ]
    }
  },
  "comp_level": "qm",
  "event_key": "2023oktu",
  "key": "2023oktu_qm20",
  "match_number": 20,
  "post_result_time": 1680885880,
  "predicted_time": 1680885676,
  "score_breakdown": {
    "blue": {
      "activationBonusAchieved": false,
      "adjustPoints": 0,
      "autoBridgeState": "Level",
      "autoChargeStationPoints": 0,
      "autoChargeStationRobot1": "None",
      "autoChargeStationRobot2": "None",
      "autoChargeStationRobot3": "None",
      "autoCommunity": {
        "B": [
          "None",
          "None",
          "None",
          "None",
          "None",
          "None",
          "None",
          "None",
          "Cone"
        ],
        "M": [
          "None",
          "None",
          "None",
          "None",
          "None",
          "None",
          "None",
          "None",
          "None"
        ],
        "T": [
          "None",
          "None",
          "None",
          "None",
          "None",
          "None",
          "None",
          "None",
          "None"
        ]
      },
      "autoDocked": false,
      "autoGamePieceCount": 1,
      "autoGamePiecePoints": 3,
      "autoMobilityPoints": 3,
      "autoPoints": 6,
      "coopGamePieceCount": 1,
      "coopertitionCriteriaMet": false,
      "endGameBridgeState": "NotLevel",
      "endGameChargeStationPoints": 0,
      "endGameChargeStationRobot1": "Park",
      "endGameChargeStationRobot2": "Park",
      "endGameChargeStationRobot3": "Park",
      "endGameParkPoints": 6,
      "foulCount": 1,
      "foulPoints": 15,
      "linkPoints": 0,
      "links": [],
      "mobilityRobot1": "Yes",
      "mobilityRobot2": "No",
      "mobilityRobot3": "No",
      "rp": 0,
      "sustainabilityBonusAchieved": false,
      "techFoulCount": 2,
      "teleopCommunity": {
        "B": [
          "Cone",
          "Cone",
          "None",
          "None",
          "None",
          "None",
          "Cone",
          "None",
          "Cone"
        ],
        "M": [
          "None",
          "None",
          "None",
          "None",
          "None",
          "Cone",
          "Cone",
          "None",
          "None"
        ],
        "T": [
          "None",
          "None",
          "None",
          "None",
          "None",
          "None",
          "None",
          "None",
          "None"
        ]
      },
      "teleopGamePieceCount": 6,
      "teleopGamePiecePoints": 12,
      "teleopPoints": 18,
      "totalChargeStationPoints": 0,
      "totalPoints": 39
    },
    "red": {
      "activationBonusAchieved": false,
      "adjustPoints": 0,
      "autoBridgeState": "Level",
      "autoChargeStationPoints": 0,
      "autoChargeStationRobot1": "None",
      "autoChargeStationRobot2": "None",
      "autoChargeStationRobot3": "None",
      "autoCommunity": {
        "B": [
          "Cone",
          "None",
          "None",
          "None",
          "None",
          "None",
          "None",
          "None",
          "None"
        ],
        "M": [
          "None",
          "None",
          "None",
          "None",
          "None",
          "None",
          "None",
          "None",
          "None"
        ],
        "T": [
          "None",
          "None",
          "None",
          "None",
          "None",
          "None",
          "None",
          "None",
          "None"
        ]
      },
      "autoDocked": false,
      "autoGamePieceCount": 1,
      "autoGamePiecePoints": 3,
      "autoMobilityPoints": 3,
      "autoPoints": 6,
      "coopGamePieceCount": 4,
      "coopertitionCriteriaMet": true,
      "endGameBridgeState": "Level",
      "endGameChargeStationPoints": 20,
      "endGameChargeStationRobot1": "Docked",
      "endGameChargeStationRobot2": "None",
      "endGameChargeStationRobot3": "Docked",
      "endGameParkPoints": 0,
      "foulCount": 3,
      "foulPoints": 29,
      "linkPoints": 10,
      "links": [
        {
          "nodes": [
            0,
            1,
            2
          ],
          "row": "Bottom"
        },
        {
          "nodes": [
            3,
            4,
            5
          ],
          "row": "Bottom"
        }
      ],
      "mobilityRobot1": "Yes",
      "mobilityRobot2": "No",
      "mobilityRobot3": "No",
      "rp": 2,
      "sustainabilityBonusAchieved": false,
      "techFoulCount": 0,
      "teleopCommunity": {
        "B": [
          "Cone",
          "Cone",
          "Cone",
          "Cube",
          "Cube",
          "Cube",
          "Cube",
          "Cube",
          "None"
        ],
        "M": [
          "None",
          "None",
          "None",
          "None",
          "Cube",
          "None",
          "None",
          "None",
          "None"
        ],
        "T": [
          "None",
          "None",
          "None",
          "None",
          "None",
          "None",
          "None",
          "None",
          "None"
        ]
      },
      "teleopGamePieceCount": 9,
      "teleopGamePiecePoints": 17,
      "teleopPoints": 37,
      "totalChargeStationPoints": 20,
      "totalPoints": 82
    }
  },
  "set_number": 1,
  "time": 1680885120,
  "videos": [
    {
      "key": "JbdP9wIT9LQ",
      "type": "youtube"
    }
  ],
  "winning_alliance": "red"
}