{
  "actual_time": 1524755101,
  "alliances": {
    "blue": {
      "dq_team_keys": [],
      "score": 516,
      "surrogate_team_keys": [],
      "team_keys": [
        "frc85",
        "frc3098",
        "frc527"
      ]
    },
    "red": {
      "dq_team_keys": [],
      "score": 246,
      "surrogate_team_keys": [],
      "team_keys": [
        "frc6911",
        "frc319",
        "frc2609"
      ]
    }
  },
  "comp_level": "qm",
  "event_key": "2018tes",
  "key": "2018tes_qm23",
  "match_number": 23,
  "post_result_time": 1524755272,
  "predicted_time": 1524755102,
  "score_breakdown": {
    "blue": {
      "adjustPoints": 0,
      "autoOwnershipPoints": 34,
      "autoPoints": 44,
      "autoQuestRankingPoint": false,
      "autoRobot1": "AutoRun",
      "autoRobot2": "AutoRun",
      "autoRobot3": "None",
      "autoRunPoints": 10,
      "autoScaleOwnershipSec": 8,
      "autoSwitchAtZero": true,
      "autoSwitchOwnershipSec": 9,
      "endgamePoints": 90,
      "endgameRobot1": "Climbing",
      "endgameRobot2": "Climbing",
      "endgameRobot3": "Levitate",
      "faceTheBossRankingPoint": true,
      "foulCount": 1,
      "foulPoints": 50,
      "rp": 3,
      "tba_gameData": "LLL",
      "techFoulCount": 0,
      "teleopOwnershipPoints": 292,
      "teleopPoints": 422,
      "teleopScaleBoostSec": 10,
      "teleopScaleForceSec": 0,
      "teleopScaleOwnershipSec": 136,
      "teleopSwitchBoostSec": 10,
      "teleopSwitchForceSec": 10,
      "teleopSwitchOwnershipSec": 136,
      "totalPoints": 516,
      "vaultBoostPlayed": 3,
      "vaultBoostTotal": 3,
      "vaultForcePlayed": 1,
      "vaultForceTotal": 2,
      "vaultLevitatePlayed": 3,
      "vaultLevitateTotal": 3,
      "vaultPoints": 40
    },
    "red": {
      "adjustPoints": 0,
      "autoOwnershipPoints": 20,
      "autoPoints": 35,
      "autoQuestRankingPoint": true,
      "autoRobot1": "AutoRun",
      "autoRobot2": "AutoRun",
      "autoRobot3": "AutoRun",
      "autoRunPoints": 15,
      "autoScaleOwnershipSec": 0,
      "autoSwitchAtZero": true,
      "autoSwitchOwnershipSec": 10,
      "endgamePoints": 90,
      "endgameRobot1": "Climbing",
      "endgameRobot2": "Climbing",
      "endgameRobot3": "Levitate",
      "faceTheBossRankingPoint": true,
      "foulCount": 0,
      "foulPoints": 5,
      "rp": 2,
      "tba_gameData": "LLL",
      "techFoulCount": 2,
      "teleopOwnershipPoints": 96,
      "teleopPoints": 206,
      "teleopScaleBoostSec": 0,
      "teleopScaleForceSec": 0,
      "teleopScaleOwnershipSec": 0,
      "teleopSwitchBoostSec": 10,
      "teleopSwitchForceSec": 0,
      "teleopSwitchOwnershipSec": 86,
      "totalPoints": 246,
      "vaultBoostPlayed": 1,
      "vaultBoostTotal": 1,
      "vaultForcePlayed": 0,
      "vaultForceTotal": 0,
      "vaultLevitatePlayed": 3,
      "vaultLevitateTotal": 3,
      "vaultPoints": 20
    }
  },
  "set_number": 1,
  "time": 1524755040,
  "videos": [
    {
      "key": "u199HJ-eC0w",
      "type": "youtube"
    },
    {
      "key": "W2z7-BaRNh8",
      "type": "youtube"
    }
  ],
  "winning_alliance": "blue"
}