{
  "actual_time": 1563047651,
  "alliances": {
    "blue": {
      "dq_team_keys": [],
      "score": 92,
      "surrogate_team_keys": [],
      "team_keys": [
        "frc930",
        "frc6443",
        "frc3538"
      ]
    },
    "red": {
      "dq_team_keys": [],
      "score": 83,
      "surrogate_team_keys": [],
      "team_keys": [
        "frc2481",
        "frc2767",
        "frc225"
      ]
    }
  },
  "comp_level": "sf",
  "event_key": "2019iri",
  "key": "2019iri_sf2m1",
  "match_number": 1,
  "post_result_time": 1563047856,
  "predicted_time": 1563047641,
  "score_breakdown": {
    "blue": {
      "adjustPoints": 0,
      "autoPoints": 15,
      "bay1": "PanelAndCargo",
      "bay2": "PanelAndCargo",
      "bay3": "PanelAndCargo",
      "bay4": "PanelAndCargo",
      "bay5": "Panel",
      "bay6": "PanelAndCargo",
      "bay7": "PanelAndCargo",
      "bay8": "PanelAndCargo",
      "cargoPoints": 45,
      "completeRocketRankingPoint": false,
      "completedRocketFar": false,
      "completedRocketNear": false,
      "endgameRobot1": "HabLevel1",
      "endgameRobot2": "HabLevel1",
      "endgameRobot3": "HabLevel2",
      "foulCount": 0,
      "foulPoints": 0,
      "habClimbPoints": 12,
      "habDockingRankingPoint": false,
      "habLineRobot1": "CrossedHabLineInSandstorm",
      "habLineRobot2": "CrossedHabLineInSandstorm",
      "habLineRobot3": "CrossedHabLineInSandstorm",
      "hatchPanelPoints": 20,
      "lowLeftRocketFar": "PanelAndCargo",
      "lowLeftRocketNear": "PanelAndCargo",
      "lowRightRocketFar": "PanelAndCargo",
      "lowRightRocketNear": "PanelAndCargo",
      "midLeftRocketFar": "PanelAndCargo",
      "midLeftRocketNear": "PanelAndCargo",
      "midRightRocketFar": "PanelAndCargo",
      "midRightRocketNear": "PanelAndCargo",
      "preMatchBay1": "Panel",
      "preMatchBay2": "Panel",
      "preMatchBay3": "Panel",
      "preMatchBay6": "Panel",
      "preMatchBay7": "Panel",
      "preMatchBay8": "Panel",
      "preMatchLevelRobot1": "HabLevel1",
      "preMatchLevelRobot2": "HabLevel2",
      "preMatchLevelRobot3": "HabLevel2",
      "rp": 0,
      "sandStormBonusPoints": 15,
      "techFoulCount": 0,
      "teleopPoints": 77,
      "topLeftRocketFar": "None",
      "topLeftRocketNear": "None",
      "topRightRocketFar": "None",
      "topRightRocketNear": "None",
      "totalPoints": 92
    },
    "red": {
      "adjustPoints": 0,
      "autoPoints": 15,
      "bay1": "PanelAndCargo",
      "bay2": "PanelAndCargo",
      "bay3": "PanelAndCargo",
      "bay4": "PanelAndCargo",
      "bay5": "PanelAndCargo",
      "bay6": "PanelAndCargo",
      "bay7": "Panel",
      "bay8": "Panel",
      "cargoPoints": 36,
      "completeRocketRankingPoint": false,
      "completedRocketFar": false,
      "completedRocketNear": false,
      "endgameRobot1": "HabLevel1",
      "endgameRobot2": "HabLevel2",
      "endgameRobot3": "HabLevel1",
      "foulCount": 0,
      "foulPoints": 0,
      "habClimbPoints": 12,
      "habDockingRankingPoint": false,
      "habLineRobot1": "CrossedHabLineInSandstorm",
      "habLineRobot2": "CrossedHabLineInSandstorm",
      "habLineRobot3": "CrossedHabLineInSandstorm",
      "hatchPanelPoints": 20,
      "lowLeftRocketFar": "PanelAndCargo",
      "lowLeftRocketNear": "PanelAndCargo",
      "lowRightRocketFar": "PanelAndCargo",
      "lowRightRocketNear": "PanelAndCargo",
      "midLeftRocketFar": "Panel",
      "midLeftRocketNear": "PanelAndCargo",
      "midRightRocketFar": "Panel",
      "midRightRocketNear": "PanelAndCargo",
      "preMatchBay1": "Panel",
      "preMatchBay2": "Panel",
      "preMatchBay3": "Panel",
      "preMatchBay6": "Panel",
      "preMatchBay7": "Panel",
      "preMatchBay8": "Panel",
      "preMatchLevelRobot1": "HabLevel2",
      "preMatchLevelRobot2": "HabLevel1",
      "preMatchLevelRobot3": "HabLevel2",
      "rp": 0,
      "sandStormBonusPoints": 15,
      "techFoulCount": 0,
      "teleopPoints": 68,
      "topLeftRocketFar": "None",
      "topLeftRocketNear": "None",
      "topRightRocketFar": "None",
      "topRightRocketNear": "None",
      "totalPoints": 83
    }
  },
  "set_number": 2,
  "time": 1563046260,
  "videos": [
    {
      "key": "zQI8C8KmHqk",
      "type": "youtube"
    }
  ],
  "winning_alliance": "blue"
}