{
  "actual_time": 1521411399,
  "alliances": {
    "blue": {
      "dq_team_keys": [],
      "score": 211,
      "surrogate_team_keys": [],
      "team_keys": [
        "frc4469",
        "frc488",
        "frc3574"
      ]
    },
    "red": {
      "dq_team_keys": [],
      "score": 372,
      "surrogate_team_keys": [],
      "team_keys": [
        "frc2557",
        "frc2046",
        "frc3049"
      ]
    }
  },
  "comp_level": "sf",
  "event_key": "2018waahs",
  "key": "2018waahs_sf2m2",
  "match_number": 2,
  "post_result_time": 1521411595,
  "predicted_time": 1521411361,
  "score_breakdown": {
    "blue": {
      "adjustPoints": 0,
      "autoOwnershipPoints": 4,
      "autoPoints": 14,
      "autoQuestRankingPoint": false,
      "autoRobot1": "AutoRun",
      "autoRobot2": "AutoRun",
      "autoRobot3": "None",
      "autoRunPoints": 10,
      "autoScaleOwnershipSec": 0,
      "autoSwitchAtZero": true,
      "autoSwitchOwnershipSec": 2,
      "endgamePoints": 35,
      "endgameRobot1": "Climbing",
      "endgameRobot2": "Parking",
      "endgameRobot3": "None",
      "faceTheBossRankingPoint": false,
      "foulCount": 0,
      "foulPoints": 10,
      "rp": 0,
      "tba_gameData": "RLR",
      "techFoulCount": 1,
      "teleopOwnershipPoints": 147,
      "teleopPoints": 187,
      "teleopScaleBoostSec": 0,
      "teleopScaleForceSec": 0,
      "teleopScaleOwnershipSec": 5,
      "teleopSwitchBoostSec": 6,
      "teleopSwitchForceSec": 0,
      "teleopSwitchOwnershipSec": 136,
      "totalPoints": 211,
      "vaultBoostPlayed": 1,
      "vaultBoostTotal": 1,
      "vaultForcePlayed": 0,
      "vaultForceTotal": 0,
      "vaultLevitatePlayed": 0,
      "vaultLevitateTotal": 0,
      "vaultPoints": 5
    },
    "red": {
      "adjustPoints": 0,
      "autoOwnershipPoints": 28,
      "autoPoints": 43,
      "autoQuestRankingPoint": false,
      "autoRobot1": "AutoRun",
      "autoRobot2": "AutoRun",
      "autoRobot3": "AutoRun",
      "autoRunPoints": 15,
      "autoScaleOwnershipSec": 7,
      "autoSwitchAtZero": true,
      "autoSwitchOwnershipSec": 7,
      "endgamePoints": 35,
      "endgameRobot1": "Parking",
      "endgameRobot2": "Climbing",
      "endgameRobot3": "None",
      "faceTheBossRankingPoint": false,
      "foulCount": 2,
      "foulPoints": 25,
      "rp": 0,
      "tba_gameData": "RLR",
      "techFoulCount": 0,
      "teleopOwnershipPoints": 259,
      "teleopPoints": 304,
      "teleopScaleBoostSec": 0,
      "teleopScaleForceSec": 0,
      "teleopScaleOwnershipSec": 125,
      "teleopSwitchBoostSec": 0,
      "teleopSwitchForceSec": 0,
      "teleopSwitchOwnershipSec": 134,
      "totalPoints": 372,
      "vaultBoostPlayed": 0,
      "vaultBoostTotal": 0,
      "vaultForcePlayed": 0,
      "vaultForceTotal": 0,
      "vaultLevitatePlayed": 0,
      "vaultLevitateTotal": 2,
      "vaultPoints": 10
    }
  },
  "set_number": 2,
  "time": 1521410220,
  "videos": [
    {
      "key": "EHMLC-4aqKc",
      "type": "youtube"
    }
  ],
  "winning_alliance": "red"
}