{
  "actual_time": 1711224576,
  "alliances": {
    "blue": {
      "dq_team_keys": [],
      "score": 33,
      "surrogate_team_keys": [],
      "team_keys": [
        "frc6723",
        "frc1027",
        "frc7127"
      ]
    },
    "red": {
      "dq_team_keys": [],
      "score": 102,
      "surrogate_team_keys": [],
      "team_keys": [
        "frc7153",
        "frc1740",
        "frc558"
      ]
    }
  },
  "comp_level": "qm",
  "event_key": "2024mawne",
  "key": "2024mawne_qm23",
  "match_number": 23,
  "post_result_time": 1711224858,
  "predicted_time": 1711240687,
  "score_breakdown": {
    "blue": {
      "adjustPoints": 0,
      "autoAmpNoteCount": 1,
      "autoAmpNotePoints": 2,
      "autoLeavePoints": 2,
      "autoLineRobot1": "No",
      "autoLineRobot2": "No",
      "autoLineRobot3": "Yes",
      "autoPoints": 14,
      "autoSpeakerNoteCount": 2,
      "autoSpeakerNotePoints": 10,
      "autoTotalNotePoints": 12,
      "coopNotePlayed": true,
      "coopertitionBonusAchieved": false,
      "coopertitionCriteriaMet": true,
      "endGameHarmonyPoints": 0,
      "endGameNoteInTrapPoints": 0,
      "endGameOnStagePoints": 0,
      "endGameParkPoints": 1,
      "endGameRobot1": "Parked",
      "endGameRobot2": "None",
      "endGameRobot3": "None",
      "endGameSpotLightBonusPoints": 0,
      "endGameTotalStagePoints": 1,
      "ensembleBonusAchieved": false,
      "ensembleBonusOnStageRobotsThreshold": 2,
      "ensembleBonusStagePointsThreshold": 10,
      "foulCount": 1,
      "foulPoints": 5,
      "g206Penalty": false,
      "g408Penalty": false,
      "g424Penalty": true,
      "melodyBonusAchieved": false,
      "melodyBonusThreshold": 18,
      "melodyBonusThresholdCoop": 15,
      "melodyBonusThresholdNonCoop": 18,
      "micCenterStage": false,
      "micStageLeft": false,
      "micStageRight": false,
      "rp": 0,
      "techFoulCount": 2,
      "teleopAmpNoteCount": 2,
      "teleopAmpNotePoints": 2,
      "teleopPoints": 14,
      "teleopSpeakerNoteAmplifiedCount": 1,
      "teleopSpeakerNoteAmplifiedPoints": 5,
      "teleopSpeakerNoteCount": 3,
      "teleopSpeakerNotePoints": 6,
      "teleopTotalNotePoints": 13,
      "totalPoints": 33,
      "trapCenterStage": false,
      "trapStageLeft": false,
      "trapStageRight": false
    },
    "red": {
      "adjustPoints": 0,
      "autoAmpNoteCount": 0,
      "autoAmpNotePoints": 0,
      "autoLeavePoints": 2,
      "autoLineRobot1": "No",
      "autoLineRobot2": "Yes",
      "autoLineRobot3": "No",
      "autoPoints": 37,
      "autoSpeakerNoteCount": 7,
      "autoSpeakerNotePoints": 35,
      "autoTotalNotePoints": 35,
      "coopNotePlayed": false,
      "coopertitionBonusAchieved": false,
      "coopertitionCriteriaMet": false,
      "endGameHarmonyPoints": 2,
      "endGameNoteInTrapPoints": 0,
      "endGameOnStagePoints": 9,
      "endGameParkPoints": 0,
      "endGameRobot1": "StageLeft",
      "endGameRobot2": "StageRight",
      "endGameRobot3": "StageRight",
      "endGameSpotLightBonusPoints": 0,
      "endGameTotalStagePoints": 11,
      "ensembleBonusAchieved": true,
      "ensembleBonusOnStageRobotsThreshold": 2,
      "ensembleBonusStagePointsThreshold": 10,
      "foulCount": 0,
      "foulPoints": 12,
      "g206Penalty": false,
      "g408Penalty": false,
      "g424Penalty": false,
      "melodyBonusAchieved": true,
      "melodyBonusThreshold": 18,
      "melodyBonusThresholdCoop": 15,
      "melodyBonusThresholdNonCoop": 18,
      "micCenterStage": false,
      "micStageLeft": false,
      "micStageRight": false,
      "rp": 4,
      "techFoulCount": 1,
      "teleopAmpNoteCount": 7,
      "teleopAmpNotePoints": 7,
      "teleopPoints": 53,
      "teleopSpeakerNoteAmplifiedCount": 5,
      "teleopSpeakerNoteAmplifiedPoints": 25,
      "teleopSpeakerNoteCount": 5,
      "teleopSpeakerNotePoints": 10,
      "teleopTotalNotePoints": 42,
      "totalPoints": 102,
      "trapCenterStage": false,
      "trapStageLeft": false,
      "trapStageRight": false
    }
  },
  "set_number": 1,
  "time": 1711220280,
  "videos": [
    {
      "key": "wKzFBjHyxd8",
      "type": "youtube"
    }
  ],
  "winning_alliance": "red"
}