{
  "actual_time": 1649519688,
  "alliances": {
    "blue": {
      "dq_team_keys": [],
      "score": 52,
      "surrogate_team_keys": [],
      "team_keys": [
        "frc4039",
        "frc8089",
        "frc4252"
      ]
    },
    "red": {
      "dq_team_keys": [],
      "score": 91,
      "surrogate_team_keys": [],
      "team_keys": [
        "frc4617",
        "frc4917",
        "frc2056"
      ]
    }
  },
  "comp_level": "qm",
  "event_key": "2022on409",
  "key": "2022on409_qm12",
  "match_number": 12,
  "post_result_time": 1649519906,
  "predicted_time": 1649519783,
  "score_breakdown": {
    "blue": {
      "adjustPoints": 0,
      "autoCargoLowerBlue": 0,
      "autoCargoLowerFar": 0,
      "autoCargoLowerNear": 0,
      "autoCargoLowerRed": 0,
      "autoCargoPoints": 12,
      "autoCargoTotal": 3,
      "autoCargoUpperBlue": 1,
      "autoCargoUpperFar": 0,
      "autoCargoUpperNear": 0,
      "autoCargoUpperRed": 2,
      "autoPoints": 16,
      "autoTaxiPoints": 4,
      "cargoBonusRankingPoint": false,
      "endgamePoints": 10,
      "endgameRobot1": "High",
      "endgameRobot2": "None",
      "endgameRobot3": "None",
      "foulCount": 0,
      "foulPoints": 4,
      "hangarBonusRankingPoint": false,
      "matchCargoTotal": 14,
      "quintetAchieved": false,
      "rp": 0,
      "taxiRobot1": "Yes",
      "taxiRobot2": "Yes",
      "taxiRobot3": "No",
      "techFoulCount": 0,
      "teleopCargoLowerBlue": 0,
      "teleopCargoLowerFar": 0,
      "teleopCargoLowerNear": 0,
      "teleopCargoLowerRed": 0,
      "teleopCargoPoints": 22,
      "teleopCargoTotal": 11,
      "teleopCargoUpperBlue": 2,
      "teleopCargoUpperFar": 2,
      "teleopCargoUpperNear": 3,
      "teleopCargoUpperRed": 4,
      "teleopPoints": 32,
      "totalPoints": 52
    },
    "red": {
      "adjustPoints": 0,
      "autoCargoLowerBlue": 0,
      "autoCargoLowerFar": 0,
      "autoCargoLowerNear": 0,
      "autoCargoLowerRed": 0,
      "autoCargoPoints": 16,
      "autoCargoTotal": 4,
      "autoCargoUpperBlue": 1,
      "autoCargoUpperFar": 1,
      "autoCargoUpperNear": 0,
      "autoCargoUpperRed": 2,
      "autoPoints": 22,
      "autoTaxiPoints": 6,
      "cargoBonusRankingPoint": true,
      "endgamePoints": 21,
      "endgameRobot1": "Mid",
      "endgameRobot2": "Traversal",
      "endgameRobot3": "None",
      "foulCount": 1,
      "foulPoints": 0,
      "hangarBonusRankingPoint": true,
      "matchCargoTotal": 28,
      "quintetAchieved": false,
      "rp": 4,
      "taxiRobot1": "Yes",
      "taxiRobot2": "Yes",
      "taxiRobot3": "Yes",
      "techFoulCount": 0,
      "teleopCargoLowerBlue": 0,
      "teleopCargoLowerFar": 0,
      "teleopCargoLowerNear": 0,
      "teleopCargoLowerRed": 0,
      "teleopCargoPoints": 48,
      "teleopCargoTotal": 24,
      "teleopCargoUpperBlue": 6,
      "teleopCargoUpperFar": 9,
      "teleopCargoUpperNear": 3,
      "teleopCargoUpperRed": 6,
      "teleopPoints": 69,
      "totalPoints": 91
    }
  },
  "set_number": 1,
  "time": 1649518080,
  "videos": [
    {
      "key": "6GMj3iETv1Y",
      "type": "youtube"
    },
    {
      "key": "kKvAwPHL15E",
      "type": "youtube"
    }
  ],
  "winning_alliance": "red"
}