{
  "actual_time": null,
  "alliances": {
    "blue": {
      "dq_team_keys": [],
      "score": 23,
      "surrogate_team_keys": [],
      "team_keys": [
        "frc1910",
        "frc967",
        "frc1329"
      ]
    },
    "red": {
      "dq_team_keys": [],
      "score": 34,
      "surrogate_team_keys": [],
      "team_keys": [
        "frc650",
        "frc1094",
        "frc1444"
      ]
    }
  },
  "comp_level": "qm",
  "event_key": "2006mo",
  "key": "2006mo_qm51",
  "match_number": 51,
  "post_result_time": null,
  "predicted_time": null,
  "score_breakdown": null,
  "set_number": 1,
  "time": null,
  "videos": [],
  "winning_alliance": "red"
}