{
  "actual_time": null,
  "alliances": {
    "blue": {
      "dq_team_keys": [],
      "score": 107,
      "surrogate_team_keys": [],
      "team_keys": [
        "frc4555",
        "frc58",
        "frc3467"
      ]
    },
    "red": {
      "dq_team_keys": [],
      "score": 122,
      "surrogate_team_keys": [],
      "team_keys": [
        "frc3280",
        "frc213",
        "frc319"
      ]
    }
  },
  "comp_level": "sf",
  "event_key": "2014nhdur",
  "key": "2014nhdur_sf2m2",
  "match_number": 2,
  "post_result_time": null,
  "predicted_time": null,
  "score_breakdown": null,
  "set_number": 2,
  "time": 1394225100,
  "videos": [
    {
      "key": "-OSL2f7EcNc",
      "type": "youtube"
    },
    {
      "key": "vGhUFv4wpZg",
      "type": "youtube"
    },
    {
      "key": "epBa2p2GhGQ",
      "type": "youtube"
    }
  ],
  "winning_alliance": "red"
}