{
  "actual_time": 1743342959,
  "alliances": {
    "blue": {
      "dq_team_keys": [],
      "score": 89,
      "surrogate_team_keys": [],
      "team_keys": [
        "frc6512",
        "frc4816",
        "frc6894"
      ]
    },
    "red": {
      "dq_team_keys": [],
      "score": 49,
      "surrogate_team_keys": [],
      "team_keys": [
        "frc8304",
        "frc8205",
        "frc9724"
      ]
    }
  },
  "comp_level": "qm",
  "event_key": "2025ncpem",
  "key": "2025ncpem_qm51",
  "match_number": 51,
  "post_result_time": 1743343151,
  "predicted_time": 1743342974,
  "score_breakdown": {
    "blue": {
      "adjustPoints": 0,
      "algaePoints": 36,
      "autoBonusAchieved": true,
      "autoCoralCount": 2,
      "autoCoralPoints": 6,
      "autoLineRobot1": "Yes",
      "autoLineRobot2": "Yes",
      "autoLineRobot3": "Yes",
      "autoMobilityPoints": 9,
      "autoPoints": 15,
      "autoReef": {
        "botRow": {
          "nodeA": false,
          "nodeB": false,
          "nodeC": false,
          "nodeD": false,
          "nodeE": false,
          "nodeF": false,
          "nodeG": false,
          "nodeH": false,
          "nodeI": false,
          "nodeJ": false,
          "nodeK": false,
          "nodeL": false
        },
        "midRow": {
          "nodeA": false,
          "nodeB": false,
          "nodeC": false,
          "nodeD": false,
          "nodeE": false,
          "nodeF": false,
          "nodeG": false,
          "nodeH": false,
          "nodeI": false,
          "nodeJ": false,
          "nodeK": false,
          "nodeL": false
        },
        "tba_botRowCount": 0,
        "tba_midRowCount": 0,
        "tba_topRowCount": 0,
        "topRow": {
          "nodeA": false,
          "nodeB": false,
          "nodeC": false,
          "nodeD": false,
          "nodeE": false,
          "nodeF": false,
          "nodeG": false,
          "nodeH": false,
          "nodeI": false,
          "nodeJ": false,
          "nodeK": false,
          "nodeL": false
        },
        "trough": 2
      },
      "bargeBonusAchieved": true,
      "coopertitionCriteriaMet": true,
      "coralBonusAchieved": false,
      "endGameBargePoints": 14,
      "endGameRobot1": "DeepCage",
      "endGameRobot2": "Parked",
      "endGameRobot3": "None",
      "foulCount": 0,
      "foulPoints": 0,
      "g206Penalty": false,
      "g410Penalty": false,
      "g418Penalty": false,
      "g428Penalty": false,
      "netAlgaeCount": 3,
      "rp": 5,
      "techFoulCount": 0,
      "teleopCoralCount": 6,
      "teleopCoralPoints": 24,
      "teleopPoints": 74,
      "teleopReef": {
        "botRow": {
          "nodeA": false,
          "nodeB": false,
          "nodeC": false,
          "nodeD": false,
          "nodeE": false,
          "nodeF": false,
          "nodeG": false,
          "nodeH": false,
          "nodeI": false,
          "nodeJ": false,
          "nodeK": false,
          "nodeL": false
        },
        "midRow": {
          "nodeA": false,
          "nodeB": false,
          "nodeC": true,
          "nodeD": true,
          "nodeE": true,
          "nodeF": true,
          "nodeG": true,
          "nodeH": true,
          "nodeI": false,
          "nodeJ": false,
          "nodeK": false,
          "nodeL": false
        },
        "tba_botRowCount": 0,
        "tba_midRowCount": 6,
        "tba_topRowCount": 0,
        "topRow": {
          "nodeA": false,
          "nodeB": false,
          "nodeC": false,
          "nodeD": false,
          "nodeE": false,
          "nodeF": false,
          "nodeG": false,
          "nodeH": false,
          "nodeI": false,
          "nodeJ": false,
          "nodeK": false,
          "nodeL": false
        },
        "trough": 0
      },
      "totalPoints": 89,
      "wallAlgaeCount": 4
    },
    "red": {
      "adjustPoints": 0,
      "algaePoints": 34,
      "autoBonusAchieved": false,
      "autoCoralCount": 0,
      "autoCoralPoints": 0,
      "autoLineRobot1": "Yes",
      "autoLineRobot2": "Yes",
      "autoLineRobot3": "Yes",
      "autoMobilityPoints": 9,
      "autoPoints": 9,
      "autoReef": {
        "botRow": {
          "nodeA": false,
          "nodeB": false,
          "nodeC": false,
          "nodeD": false,
          "nodeE": false,
          "nodeF": false,
          "nodeG": false,
          "nodeH": false,
          "nodeI": false,
          "nodeJ": false,
          "nodeK": false,
          "nodeL": false
        },
        "midRow": {
          "nodeA": false,
          "nodeB": false,
          "nodeC": false,
          "nodeD": false,
          "nodeE": false,
          "nodeF": false,
          "nodeG": false,
          "nodeH": false,
          "nodeI": false,
          "nodeJ": false,
          "nodeK": false,
          "nodeL": false
        },
        "tba_botRowCount": 0,
        "tba_midRowCount": 0,
        "tba_topRowCount": 0,
        "topRow": {
          "nodeA": false,
          "nodeB": false,
          "nodeC": false,
          "nodeD": false,
          "nodeE": false,
          "nodeF": false,
          "nodeG": false,
          "nodeH": false,
          "nodeI": false,
          "nodeJ": false,
          "nodeK": false,
          "nodeL": false
        },
        "trough": 0
      },
      "bargeBonusAchieved": false,
      "coopertitionCriteriaMet": true,
      "coralBonusAchieved": false,
      "endGameBargePoints": 4,
      "endGameRobot1": "Parked",
      "endGameRobot2": "None",
      "endGameRobot3": "Parked",
      "foulCount": 0,
      "foulPoints": 0,
      "g206Penalty": false,
      "g410Penalty": false,
      "g418Penalty": false,
      "g428Penalty": false,
      "netAlgaeCount": 4,
      "rp": 0,
      "techFoulCount": 0,
      "teleopCoralCount": 1,
      "teleopCoralPoints": 2,
      "teleopPoints": 40,
      "teleopReef": {
        "botRow": {
          "nodeA": false,
          "nodeB": false,
          "nodeC": false,
          "nodeD": false,
          "nodeE": false,
          "nodeF": false,
          "nodeG": false,
          "nodeH": false,
          "nodeI": false,
          "nodeJ": false,
          "nodeK": false,
          "nodeL": false
        },
        "midRow": {
          "nodeA": false,
          "nodeB": false,
          "nodeC": false,
          "nodeD": false,
          "nodeE": false,
          "nodeF": false,
          "nodeG": false,
          "nodeH": false,
          "nodeI": false,
          "nodeJ": false,
          "nodeK": false,
          "nodeL": false
        },
        "tba_botRowCount": 0,
        "tba_midRowCount": 0,
        "tba_topRowCount": 0,
        "topRow": {
          "nodeA": false,
          "nodeB": false,
          "nodeC": false,
          "nodeD": false,
          "nodeE": false,
          "nodeF": false,
          "nodeG": false,
          "nodeH": false,
          "nodeI": false,
          "nodeJ": false,
          "nodeK": false,
          "nodeL": false
        },
        "trough": 1
      },
      "totalPoints": 49,
      "wallAlgaeCount": 3
    }
  },
  "set_number": 1,
  "time": 1743342960,
  "videos": [
    {
      "key": "WD2p2nTIiR4",
      "type": "youtube"
    }
  ],
  "winning_alliance": "blue"
}