{
  "actual_time": 1677886727,
  "alliances": {
    "blue": {
      "dq_team_keys": [],
      "score": 33,
      "surrogate_team_keys": [],
      "team_keys": [
        "frc5314",
        "frc4375",
        "frc6558"
      ]
    },
    "red": {
      "dq_team_keys": [],
      "score": 70,
      "surrogate_team_keys": [],
      "team_keys": [
        "frc573",
        "frc6569",
        "frc6088"
      ]
    }
  },
  "comp_level": "qm",
  "event_key": "2023miesc",
  "key": "2023miesc_qm42",
  "match_number": 42,
  "post_result_time": 1677886951,
  "predicted_time": 1677886877,
  "score_breakdown": {
    "blue": {
      "activationBonusAchieved": false,
      "adjustPoints": 0,
      "autoBridgeState": "NotLevel",
      "autoChargeStationPoints": 8,
      "autoChargeStationRobot1": "Docked",
      "autoChargeStationRobot2": "None",
      "autoChargeStationRobot3": "None",
      "autoCommunity": {
        "B": [
          "None",
          "None",
          "None",
          "None",
          "None",
          "None",
          "None",
          "None",
          "None"
        ],
        "M": [
          "None",
          "None",
          "None",
          "None",
          "None",
          "None",
          "None",
          "None",
          "None"
        ],
        "T": [
          "None",
          "None",
          "None",
          "None",
          "None",
          "None",
          "None",
          "None",
          "None"
        ]
      },
      "autoDocked": true,
      "autoGamePieceCount": 0,
      "autoGamePiecePoints": 0,
      "autoMobilityPoints": 3,
      "autoPoints": 11,
      "coopGamePieceCount": 0,
      "coopertitionCriteriaMet": false,
      "endGameBridgeState": "NotLevel",
      "endGameChargeStationPoints": 6,
      "endGameChargeStationRobot1": "Docked",
      "endGameChargeStationRobot2": "None",
      "endGameChargeStationRobot3": "None",
      "endGameParkPoints": 0,
      "foulCount": 0,
      "foulPoints": 0,
      "linkPoints": 0,
      "links": [],
      "mobilityRobot1": "No",
      "mobilityRobot2": "Yes",
      "mobilityRobot3": "No",
      "rp": 0,
      "sustainabilityBonusAchieved": false,
      "techFoulCount": 0,
      "teleopCommunity": {
        "B": [
          "Cone",
          "None",
          "Cube",
          "None",
          "None",
          "None",
          "None",
          "None",
          "Cone"
        ],
        "M": [
          "None",
          "None",
          "None",
          "None",
          "None",
          "None",
          "None",
          "None",
          "None"
        ],
        "T": [
          "None",
          "None",
          "None",
          "None",
          "None",
          "None",
          "Cone",
          "None",
          "Cone"
        ]
      },
      "teleopGamePieceCount": 5,
      "teleopGamePiecePoints": 16,
      "teleopPoints": 22,
      "totalChargeStationPoints": 14,
      "totalPoints": 33
    },
    "red": {
      "activationBonusAchieved": false,
      "adjustPoints": 0,
      "autoBridgeState": "Level",
      "autoChargeStationPoints": 0,
      "autoChargeStationRobot1": "None",
      "autoChargeStationRobot2": "None",
      "autoChargeStationRobot3": "None",
      "autoCommunity": {
        "B": [
          "None",
          "None",
          "None",
          "None",
          "None",
          "None",
          "None",
          "None",
          "None"
        ],
        "M": [
          "None",
          "None",
          "None",
          "None",
          "None",
          "None",
          "None",
          "None",
          "Cone"
        ],
        "T": [
          "None",
          "None",
          "None",
          "None",
          "None",
          "Cone",
          "None",
          "None",
          "None"
        ]
      },
      "autoDocked": false,
      "autoGamePieceCount": 2,
      "autoGamePiecePoints": 10,
      "autoMobilityPoints": 6,
      "autoPoints": 16,
      "coopGamePieceCount": 6,
      "coopertitionCriteriaMet": true,
      "endGameBridgeState": "NotLevel",
      "endGameChargeStationPoints": 6,
      "endGameChargeStationRobot1": "Park",
      "endGameChargeStationRobot2": "Docked",
      "endGameChargeStationRobot3": "None",
      "endGameParkPoints": 2,
      "foulCount": 0,
      "foulPoints": 0,
      "linkPoints": 10,
      "links": [
        {
          "nodes": [
            0,
            1,
            2
          ],
          "row": "Bottom"
        },
        {
          "nodes": [
            3,
            4,
            5
          ],
          "row": "Top"
        }
      ],
      "mobilityRobot1": "No",
      "mobilityRobot2": "Yes",
      "mobilityRobot3": "Yes",
      "rp": 2,
      "sustainabilityBonusAchieved": false,
      "techFoulCount": 0,
      "teleopCommunity": {
        "B": [
          "Cube",
          "Cube",
          "Cube",
          "Cube",
          "Cube",
          "None",
          "Cone",
          "None",
          "None"
        ],
        "M": [
          "None",
          "Cube",
          "None",
          "None",
          "Cube",
          "None",
          "Cone",
          "None",
          "Cone"
        ],
        "T": [
          "None",
          "None",
          "None",
          "Cone",
          "Cube",
          "Cone",
          "None",
          "Cube",
          "None"
        ]
      },
      "teleopGamePieceCount": 14,
      "teleopGamePiecePoints": 36,
      "teleopPoints": 44,
      "totalChargeStationPoints": 6,
      "totalPoints": 70
    }
  },
  "set_number": 1,
  "time": 1677880920,
  "videos": [
    {
      "key": "cFuXiRgzZqs",
      "type": "youtube"
    }
  ],
  "winning_alliance": "red"
}