{
  "actual_time": null,
  "alliances": {
    "blue": {
      "dq_team_keys": [],
      "score": 63,
      "surrogate_team_keys": [],
      "team_keys": [
        "frc4391",
        "frc1243",
        "frc2474"
      ]
    },
    "red": {
      "dq_team_keys": [],
      "score": 47,
      "surrogate_team_keys": [],
      "team_keys": [
        "frc2771",
        "frc27",
        "frc2054"
      ]
    }
  },
  "comp_level": "qm",
  "event_key": "2012swm",
  "key": "2012swm_qm62",
  "match_number": 62,
  "post_result_time": null,
  "predicted_time": null,
  "score_breakdown": null,
  "set_number": 1,
  "time": null,
  "videos": [
    {
      "key": "tCQuQNL-kyY",
      "type": "youtube"
    }
  ],
  "winning_alliance": "blue"
}