{
  "actual_time": 1679870239,
  "alliances": {
    "blue": {
      "dq_team_keys": [],
      "score": 116,
      "surrogate_team_keys": [],
      "team_keys": [
        "frc4738",
        "frc599",
        "frc3749"
      ]
    },
    "red": {
      "dq_team_keys": [],
      "score": 165,
      "surrogate_team_keys": [],
      "team_keys": [
        "frc4419",
        "frc973",
        "frc1538"
      ]
    }
  },
  "comp_level": "sf",
  "event_key": "2023casd",
  "key": "2023casd_sf11m1",
  "match_number": 1,
  "post_result_time": 1679870452,
  "predicted_time": 1679870222,
  "score_breakdown": {
    "blue": {
      "activationBonusAchieved": false,
      "adjustPoints": 0,
      "autoBridgeState": "Level",
      "autoChargeStationPoints": 12,
      "autoChargeStationRobot1": "None",
      "autoChargeStationRobot2": "Docked",
      "autoChargeStationRobot3": "None",
      "autoCommunity": {
        "B": [
          "Cone",
          "None",
          "None",
          "None",
          "None",
          "None",
          "None",
          "None",
          "None"
        ],
        "M": [
          "None",
          "None",
          "None",
          "None",
          "None",
          "None",
          "None",
          "None",
          "None"
        ],
        "T": [
          "None",
          "None",
          "None",
          "None",
          "Cube",
          "None",
          "None",
          "None",
          "Cone"
        ]
      },
      "autoDocked": true,
      "autoGamePieceCount": 3,
      "autoGamePiecePoints": 15,
      "autoMobilityPoints": 9,
      "autoPoints": 36,
      "coopGamePieceCount": 3,
      "coopertitionCriteriaMet": false,
      "endGameBridgeState": "Level",
      "endGameChargeStationPoints": 10,
      "endGameChargeStationRobot1": "Docked",
      "endGameChargeStationRobot2": "Park",
      "endGameChargeStationRobot3": "Park",
      "endGameParkPoints": 4,
      "foulCount": 2,
      "foulPoints": 0,
      "linkPoints": 20,
      "links": [
        {
          "nodes": [
            6,
            7,
            8
          ],
          "row": "Mid"
        },
        {
          "nodes": [
            0,
            1,
            2
          ],
          "row": "Top"
        },
        {
          "nodes": [
            3,
            4,
            5
          ],
          "row": "Top"
        },
        {
          "nodes": [
            6,
            7,
            8
          ],
          "row": "Top"
        }
      ],
      "mobilityRobot1": "Yes",
      "mobilityRobot2": "Yes",
      "mobilityRobot3": "Yes",
      "rp": 0,
      "sustainabilityBonusAchieved": false,
      "techFoulCount": 0,
      "teleopCommunity": {
        "B": [
          "Cone",
          "None",
          "None",
          "None",
          "None",
          "None",
          "None",
          "None",
          "Cone"
        ],
        "M": [
          "None",
          "None",
          "None",
          "None",
          "None",
          "None",
          "Cone",
          "Cube",
          "Cone"
        ],
        "T": [
          "Cone",
          "Cube",
          "Cone",
          "Cone",
          "Cube",
          "Cone",
          "Cone",
          "Cube",
          "Cone"
        ]
      },
      "teleopGamePieceCount": 14,
      "teleopGamePiecePoints": 46,
      "teleopPoints": 60,
      "totalChargeStationPoints": 22,
      "totalPoints": 116
    },
    "red": {
      "activationBonusAchieved": false,
      "adjustPoints": 0,
      "autoBridgeState": "NotLevel",
      "autoChargeStationPoints": 8,
      "autoChargeStationRobot1": "None",
      "autoChargeStationRobot2": "Docked",
      "autoChargeStationRobot3": "None",
      "autoCommunity": {
        "B": [
          "None",
          "None",
          "None",
          "None",
          "None",
          "None",
          "None",
          "None",
          "Cube"
        ],
        "M": [
          "Cone",
          "Cube",
          "None",
          "None",
          "None",
          "None",
          "None",
          "None",
          "None"
        ],
        "T": [
          "None",
          "None",
          "None",
          "None",
          "None",
          "Cone",
          "None",
          "None",
          "None"
        ]
      },
      "autoDocked": true,
      "autoGamePieceCount": 4,
      "autoGamePiecePoints": 17,
      "autoMobilityPoints": 9,
      "autoPoints": 34,
      "coopGamePieceCount": 6,
      "coopertitionCriteriaMet": false,
      "endGameBridgeState": "Level",
      "endGameChargeStationPoints": 30,
      "endGameChargeStationRobot1": "Docked",
      "endGameChargeStationRobot2": "Docked",
      "endGameChargeStationRobot3": "Docked",
      "endGameParkPoints": 0,
      "foulCount": 0,
      "foulPoints": 10,
      "linkPoints": 30,
      "links": [
        {
          "nodes": [
            6,
            7,
            8
          ],
          "row": "Bottom"
        },
        {
          "nodes": [
            0,
            1,
            2
          ],
          "row": "Mid"
        },
        {
          "nodes": [
            3,
            4,
            5
          ],
          "row": "Mid"
        },
        {
          "nodes": [
            0,
            1,
            2
          ],
          "row": "Top"
        },
        {
          "nodes": [
            3,
            4,
            5
          ],
          "row": "Top"
        },
        {
          "nodes": [
            6,
            7,
            8
          ],
          "row": "Top"
        }
      ],
      "mobilityRobot1": "Yes",
      "mobilityRobot2": "Yes",
      "mobilityRobot3": "Yes",
      "rp": 0,
      "sustainabilityBonusAchieved": false,
      "techFoulCount": 0,
      "teleopCommunity": {
        "B": [
          "None",
          "Cone",
          "None",
          "None",
          "None",
          "None",
          "Cone",
          "Cube",
          "Cube"
        ],
        "M": [
          "Cone",
          "Cube",
          "Cone",
          "Cone",
          "Cube",
          "Cone",
          "None",
          "None",
          "Cone"
        ],
        "T": [
          "Cone",
          "Cube",
          "Cone",
          "Cone",
          "Cube",
          "Cone",
          "Cone",
          "Cube",
          "Cone"
        ]
      },
      "teleopGamePieceCount": 20,
      "teleopGamePiecePoints": 61,
      "teleopPoints": 91,
      "totalChargeStationPoints": 38,
      "totalPoints": 165
    }
  },
  "set_number": 11,
  "time": 1679868300,
  "videos": [
    {
      "key": "ul7D1YLTL6U",
      "type": "youtube"
    },
    {
      "key": "7Leb2SXBn-Q",
      "type": "youtube"
    }
  ],
  "winning_alliance": "red"
}