{
  "actual_time": 1711235966,
  "alliances": {
    "blue": {
      "dq_team_keys": [],
      "score": 49,
      "surrogate_team_keys": [],
      "team_keys": [
        "frc753",
        "frc2471",
        "frc4043"
      ]
    },
    "red": {
      "dq_team_keys": [],
      "score": 144,
      "surrogate_team_keys": [],
      "team_keys": [
        "frc6465",
        "frc2521",
        "frc1540"
      ]
    }
  },
  "comp_level": "f",
  "event_key": "2024orwil",
  "key": "2024orwil_f1m3",
  "match_number": 3,
  "post_result_time": 1711236183,
  "predicted_time": 1711250051,
  "score_breakdown": {
    "blue": {
      "adjustPoints": 0,
      "autoAmpNoteCount": 0,
      "autoAmpNotePoints": 0,
      "autoLeavePoints": 4,
      "autoLineRobot1": "No",
      "autoLineRobot2": "Yes",
      "autoLineRobot3": "Yes",
      "autoPoints": 14,
      "autoSpeakerNoteCount": 2,
      "autoSpeakerNotePoints": 10,
      "autoTotalNotePoints": 10,
      "coopNotePlayed": false,
      "coopertitionBonusAchieved": false,
      "coopertitionCriteriaMet": false,
      "endGameHarmonyPoints": 0,
      "endGameNoteInTrapPoints": 0,
      "endGameOnStagePoints": 0,
      "endGameParkPoints": 2,
      "endGameRobot1": "Parked",
      "endGameRobot2": "Parked",
      "endGameRobot3": "None",
      "endGameSpotLightBonusPoints": 0,
      "endGameTotalStagePoints": 2,
      "ensembleBonusAchieved": false,
      "ensembleBonusOnStageRobotsThreshold": 2,
      "ensembleBonusStagePointsThreshold": 10,
      "foulCount": 0,
      "foulPoints": 0,
      "g206Penalty": false,
      "g408Penalty": false,
      "g424Penalty": false,
      "melodyBonusAchieved": false,
      "melodyBonusThreshold": 18,
      "melodyBonusThresholdCoop": 15,
      "melodyBonusThresholdNonCoop": 18,
      "micCenterStage": false,
      "micStageLeft": false,
      "micStageRight": false,
      "rp": 0,
      "techFoulCount": 7,
      "teleopAmpNoteCount": 6,
      "teleopAmpNotePoints": 6,
      "teleopPoints": 35,
      "teleopSpeakerNoteAmplifiedCount": 5,
      "teleopSpeakerNoteAmplifiedPoints": 25,
      "teleopSpeakerNoteCount": 1,
      "teleopSpeakerNotePoints": 2,
      "teleopTotalNotePoints": 33,
      "totalPoints": 49,
      "trapCenterStage": false,
      "trapStageLeft": false,
      "trapStageRight": false
    },
    "red": {
      "adjustPoints": 0,
      "autoAmpNoteCount": 0,
      "autoAmpNotePoints": 0,
      "autoLeavePoints": 6,
      "autoLineRobot1": "Yes",
      "autoLineRobot2": "Yes",
      "autoLineRobot3": "Yes",
      "autoPoints": 41,
      "autoSpeakerNoteCount": 7,
      "autoSpeakerNotePoints": 35,
      "autoTotalNotePoints": 35,
      "coopNotePlayed": false,
      "coopertitionBonusAchieved": false,
      "coopertitionCriteriaMet": false,
      "endGameHarmonyPoints": 0,
      "endGameNoteInTrapPoints": 5,
      "endGameOnStagePoints": 6,
      "endGameParkPoints": 0,
      "endGameRobot1": "None",
      "endGameRobot2": "StageLeft",
      "endGameRobot3": "StageRight",
      "endGameSpotLightBonusPoints": 0,
      "endGameTotalStagePoints": 11,
      "ensembleBonusAchieved": false,
      "ensembleBonusOnStageRobotsThreshold": 2,
      "ensembleBonusStagePointsThreshold": 10,
      "foulCount": 0,
      "foulPoints": 35,
      "g206Penalty": false,
      "g408Penalty": false,
      "g424Penalty": false,
      "melodyBonusAchieved": false,
      "melodyBonusThreshold": 18,
      "melodyBonusThresholdCoop": 15,
      "melodyBonusThresholdNonCoop": 18,
      "micCenterStage": false,
      "micStageLeft": false,
      "micStageRight": false,
      "rp": 0,
      "techFoulCount": 0,
      "teleopAmpNoteCount": 6,
      "teleopAmpNotePoints": 6,
      "teleopPoints": 68,
      "teleopSpeakerNoteAmplifiedCount": 7,
      "teleopSpeakerNoteAmplifiedPoints": 35,
      "teleopSpeakerNoteCount": 8,
      "teleopSpeakerNotePoints": 16,
      "teleopTotalNotePoints": 57,
      "totalPoints": 144,
      "trapCenterStage": false,
      "trapStageLeft": false,
      "trapStageRight": true
    }
  },
  "set_number": 1,
  "time": 1711233660,
  "videos": [
    {
      "key": "0RxBgxMaqQY",
      "type": "youtube"
    },
    {
      "key": "My_LpBamHj4",
      "type": "youtube"
    },
    {
      "key": "CCturiz5UdM",
      "type": "youtube"
    },
    {
      "key": "zy8nHrj0zM8",
      "type": "youtube"
    },
    {
      "key": "sC8gohRWRfg",
      "type": "youtube"
    },
    {
      "key": "1Evyb6GfpHw",
      "type": "youtube"
    }
  ],
  "winning_alliance": "red"
}