{
  "actual_time": 1698514963,
  "alliances": {
    "blue": {
      "dq_team_keys": [],
      "score": 89,
      "surrogate_team_keys": [],
      "team_keys": [
        "frc9998",
        "frc1899",
        "frc360"
      ]
    },
    "red": {
      "dq_team_keys": [],
      "score": 36,
      "surrogate_team_keys": [],
      "team_keys": [
        "frc6350",
        "frc2990",
        "frc4513"
      ]
    }
  },
  "comp_level": "qm",
  "event_key": "2023wamc",
  "key": "2023wamc_qm1",
  "match_number": 1,
  "post_result_time": 1698515150,
  "predicted_time": 1698515100,
  "score_breakdown": {
    "blue": {
      "activationBonusAchieved": false,
      "adjustPoints": 0,
      "autoBridgeState": "NotLevel",
      "autoChargeStationPoints": 0,
      "autoChargeStationRobot1": "None",
      "autoChargeStationRobot2": "None",
      "autoChargeStationRobot3": "None",
      "autoCommunity": {
        "B": [
          "None",
          "None",
          "None",
          "None",
          "None",
          "None",
          "None",
          "None",
          "None"
        ],
        "M": [
          "None",
          "None",
          "None",
          "None",
          "None",
          "None",
          "None",
          "None",
          "None"
        ],
        "T": [
          "None",
          "Cube",
          "None",
          "None",
          "None",
          "None",
          "None",
          "None",
          "None"
        ]
      },
      "autoDocked": false,
      "autoGamePieceCount": 1,
      "autoGamePiecePoints": 6,
      "autoMobilityPoints": 3,
      "autoPoints": 9,
      "coopGamePieceCount": 5,
      "coopertitionCriteriaMet": true,
      "endGameBridgeState": "Level",
      "endGameChargeStationPoints": 20,
      "endGameChargeStationRobot1": "Docked",
      "endGameChargeStationRobot2": "Docked",
      "endGameChargeStationRobot3": "None",
      "endGameParkPoints": 0,
      "extraGamePieceCount": 0,
      "foulCount": 0,
      "foulPoints": 0,
      "g405Penalty": false,
      "h111Penalty": false,
      "linkPoints": 15,
      "links": [
        {
          "nodes": [
            1,
            2,
            3
          ],
          "row": "Mid"
        },
        {
          "nodes": [
            0,
            1,
            2
          ],
          "row": "Top"
        },
        {
          "nodes": [
            3,
            4,
            5
          ],
          "row": "Top"
        }
      ],
      "mobilityRobot1": "No",
      "mobilityRobot2": "Yes",
      "mobilityRobot3": "No",
      "rp": 2,
      "sustainabilityBonusAchieved": false,
      "techFoulCount": 0,
      "teleopCommunity": {
        "B": [
          "None",
          "None",
          "None",
          "None",
          "None",
          "Cube",
          "None",
          "Cube",
          "Cube"
        ],
        "M": [
          "None",
          "Cube",
          "Cone",
          "Cone",
          "None",
          "None",
          "None",
          "None",
          "None"
        ],
        "T": [
          "Cone",
          "Cube",
          "Cone",
          "Cone",
          "Cube",
          "Cone",
          "Cone",
          "None",
          "None"
        ]
      },
      "teleopGamePieceCount": 13,
      "teleopGamePiecePoints": 45,
      "teleopPoints": 65,
      "totalChargeStationPoints": 20,
      "totalPoints": 89
    },
    "red": {
      "activationBonusAchieved": false,
      "adjustPoints": 0,
      "autoBridgeState": "Level",
      "autoChargeStationPoints": 0,
      "autoChargeStationRobot1": "None",
      "autoChargeStationRobot2": "None",
      "autoChargeStationRobot3": "None",
      "autoCommunity": {
        "B": [
          "Cone",
          "None",
          "None",
          "None",
          "None",
          "None",
          "None",
          "None",
          "None"
        ],
        "M": [
          "None",
          "None",
          "None",
          "None",
          "None",
          "None",
          "None",
          "None",
          "None"
        ],
        "T": [
          "None",
          "None",
          "None",
          "None",
          "None",
          "None",
          "None",
          "None",
          "None"
        ]
      },
      "autoDocked": false,
      "autoGamePieceCount": 1,
      "autoGamePiecePoints": 3,
      "autoMobilityPoints": 0,
      "autoPoints": 3,
      "coopGamePieceCount": 2,
      "coopertitionCriteriaMet": false,
      "endGameBridgeState": "NotLevel",
      "endGameChargeStationPoints": 12,
      "endGameChargeStationRobot1": "Docked",
      "endGameChargeStationRobot2": "None",
      "endGameChargeStationRobot3": "Docked",
      "endGameParkPoints": 0,
      "extraGamePieceCount": 0,
      "foulCount": 0,
      "foulPoints": 0,
      "g405Penalty": false,
      "h111Penalty": false,
      "linkPoints": 5,
      "links": [
        {
          "nodes": [
            4,
            5,
            6
          ],
          "row": "Bottom"
        }
      ],
      "mobilityRobot1": "No",
      "mobilityRobot2": "No",
      "mobilityRobot3": "No",
      "rp": 0,
      "sustainabilityBonusAchieved": false,
      "techFoulCount": 0,
      "teleopCommunity": {
        "B": [
          "Cone",
          "None",
          "None",
          "None",
          "Cube",
          "Cube",
          "Cube",
          "None",
          "None"
        ],
        "M": [
          "None",
          "None",
          "None",
          "None",
          "None",
          "None",
          "None",
          "None",
          "None"
        ],
        "T": [
          "Cone",
          "None",
          "None",
          "None",
          "None",
          "None",
          "None",
          "Cube",
          "None"
        ]
      },
      "teleopGamePieceCount": 6,
      "teleopGamePiecePoints": 16,
      "teleopPoints": 28,
      "totalChargeStationPoints": 12,
      "totalPoints": 36
    }
  },
  "set_number": 1,
  "time": 1698515100,
  "videos": [
    {
      "key": "1b5dCQbavOI",
      "type": "youtube"
    },
    {
      "key": "AKoTFYibQw8",
      "type": "youtube"
    }
  ],
  "winning_alliance": "blue"
}