{
  "actual_time": 1582995286,
  "alliances": {
    "blue": {
      "dq_team_keys": [],
      "score": 149,
      "surrogate_team_keys": [],
      "team_keys": [
        "frc4083",
        "frc5410",
        "frc4020"
      ]
    },
    "red": {
      "dq_team_keys": [],
      "score": 52,
      "surrogate_team_keys": [],
      "team_keys": [
        "frc4764",
        "frc1758",
        "frc5943"
      ]
    }
  },
  "comp_level": "qm",
  "event_key": "2020scmb",
  "key": "2020scmb_qm89",
  "match_number": 89,
  "post_result_time": 1582995458,
  "predicted_time": 1582995301,
  "score_breakdown": {
    "blue": {
      "adjustPoints": 0,
      "autoCellPoints": 24,
      "autoCellsBottom": 0,
      "autoCellsInner": 2,
      "autoCellsOuter": 3,
      "autoInitLinePoints": 15,
      "autoPoints": 39,
      "controlPanelPoints": 0,
      "endgamePoints": 65,
      "endgameRobot1": "None",
      "endgameRobot2": "Hang",
      "endgameRobot3": "Hang",
      "endgameRungIsLevel": "IsLevel",
      "foulCount": 1,
      "foulPoints": 0,
      "initLineRobot1": "Exited",
      "initLineRobot2": "Exited",
      "initLineRobot3": "Exited",
      "rp": 3,
      "shieldEnergizedRankingPoint": false,
      "shieldOperationalRankingPoint": true,
      "stage1Activated": true,
      "stage2Activated": false,
      "stage3Activated": false,
      "stage3TargetColor": "Unknown",
      "tba_numRobotsHanging": 2,
      "tba_shieldEnergizedRankingPointFromFoul": false,
      "techFoulCount": 0,
      "teleopCellPoints": 45,
      "teleopCellsBottom": 0,
      "teleopCellsInner": 3,
      "teleopCellsOuter": 18,
      "teleopPoints": 110,
      "totalPoints": 149
    },
    "red": {
      "adjustPoints": 0,
      "autoCellPoints": 8,
      "autoCellsBottom": 0,
      "autoCellsInner": 0,
      "autoCellsOuter": 2,
      "autoInitLinePoints": 10,
      "autoPoints": 18,
      "controlPanelPoints": 0,
      "endgamePoints": 15,
      "endgameRobot1": "Park",
      "endgameRobot2": "Park",
      "endgameRobot3": "Park",
      "endgameRungIsLevel": "IsLevel",
      "foulCount": 0,
      "foulPoints": 3,
      "initLineRobot1": "None",
      "initLineRobot2": "Exited",
      "initLineRobot3": "Exited",
      "rp": 0,
      "shieldEnergizedRankingPoint": false,
      "shieldOperationalRankingPoint": false,
      "stage1Activated": true,
      "stage2Activated": false,
      "stage3Activated": false,
      "stage3TargetColor": "Unknown",
      "tba_numRobotsHanging": 0,
      "tba_shieldEnergizedRankingPointFromFoul": false,
      "techFoulCount": 0,
      "teleopCellPoints": 16,
      "teleopCellsBottom": 0,
      "teleopCellsInner": 0,
      "teleopCellsOuter": 8,
      "teleopPoints": 31,
      "totalPoints": 52
    }
  },
  "set_number": 1,
  "time": 1582994040,
  "videos": [
    {
      "key": "X0kh88B8K84",
      "type": "youtube"
    }
  ],
  "winning_alliance": "blue"
}