{
  "actual_time": 1772987634,
  "alliances": {
    "blue": {
      "dq_team_keys": [],
      "score": 223,
      "surrogate_team_keys": [],
      "team_keys": [
        "frc2611",
        "frc5205",
        "frc7197"
      ]
    },
    "red": {
      "dq_team_keys": [],
      "score": 138,
      "surrogate_team_keys": [],
      "team_keys": [
        "frc6081",
        "frc7056",
        "frc10285"
      ]
    }
  },
  "comp_level": "qm",
  "event_key": "2026miche",
  "key": "2026miche_qm78",
  "match_number": 78,
  "post_result_time": 1772987839,
  "predicted_time": 1772987611,
  "score_breakdown": {
    "blue": {
      "adjustPoints": 0,
      "autoTowerPoints": 0,
      "autoTowerRobot1": "None",
      "autoTowerRobot2": "None",
      "autoTowerRobot3": "None",
      "endGameTowerPoints": 0,
      "endGameTowerRobot1": "None",
      "endGameTowerRobot2": "None",
      "endGameTowerRobot3": "None",
      "energizedAchieved": true,
      "foulPoints": 0,
      "g206Penalty": false,
      "hubScore": {
        "autoCount": 33,
        "autoPoints": 33,
        "endgameCount": 69,
        "endgamePoints": 69,
        "shift1Count": 53,
        "shift1Points": 53,
        "shift2Count": 0,
        "shift2Points": 0,
        "shift3Count": 68,
        "shift3Points": 68,
        "shift4Count": 0,
        "shift4Points": 0,
        "teleopCount": 190,
        "teleopPoints": 190,
        "totalCount": 223,
        "totalPoints": 223,
        "transitionCount": 0,
        "transitionPoints": 0,
        "uncounted": 0
      },
      "majorFoulCount": 0,
      "minorFoulCount": 0,
      "penalties": "None",
      "rp": 4,
      "superchargedAchieved": false,
      "totalAutoPoints": 33,
      "totalPoints": 223,
      "totalTeleopPoints": 190,
      "totalTowerPoints": 0,
      "traversalAchieved": false
    },
    "red": {
      "adjustPoints": 0,
      "autoTowerPoints": 0,
      "autoTowerRobot1": "None",
      "autoTowerRobot2": "None",
      "autoTowerRobot3": "None",
      "endGameTowerPoints": 10,
      "endGameTowerRobot1": "Level1",
      "endGameTowerRobot2": "None",
      "endGameTowerRobot3": "None",
      "energizedAchieved": true,
      "foulPoints": 0,
      "g206Penalty": false,
      "hubScore": {
        "autoCount": 43,
        "autoPoints": 43,
        "endgameCount": 34,
        "endgamePoints": 34,
        "shift1Count": 0,
        "shift1Points": 0,
        "shift2Count": 20,
        "shift2Points": 20,
        "shift3Count": 0,
        "shift3Points": 0,
        "shift4Count": 29,
        "shift4Points": 29,
        "teleopCount": 85,
        "teleopPoints": 85,
        "totalCount": 128,
        "totalPoints": 128,
        "transitionCount": 2,
        "transitionPoints": 2,
        "uncounted": 0
      },
      "majorFoulCount": 0,
      "minorFoulCount": 0,
      "penalties": "None",
      "rp": 1,
      "superchargedAchieved": false,
      "totalAutoPoints": 43,
      "totalPoints": 138,
      "totalTeleopPoints": 95,
      "totalTowerPoints": 10,
      "traversalAchieved": false
    }
  },
  "set_number": 1,
  "time": 1772987160,
  "videos": [
    {
      "key": "nKwUlANmizs",
      "type": "youtube"
    }
  ],
  "winning_alliance": "blue"
}