{
  "actual_time": null,
  "alliances": {
    "blue": {
      "dq_team_keys": [],
      "score": 265,
      "surrogate_team_keys": [],
      "team_keys": [
        "frc5184",
        "frc3145",
        "frc2013"
      ]
    },
    "red": {
      "dq_team_keys": [],
      "score": 83,
      "surrogate_team_keys": [],
      "team_keys": [
        "frc4625",
        "frc3216",
        "frc5078"
      ]
    }
  },
  "comp_level": "qm",
  "event_key": "2014abca",
  "key": "2014abca_qm74",
  "match_number": 74,
  "post_result_time": null,
  "predicted_time": null,
  "score_breakdown": null,
  "set_number": 1,
  "time": 1396719120,
  "videos": [
    {
      "key": "s4hUcP5nOe8",
      "type": "youtube"
    }
  ],
  "winning_alliance": "blue"
}