{
  "actual_time": 1773001297,
  "alliances": {
    "blue": {
      "dq_team_keys": [],
      "score": 123,
      "surrogate_team_keys": [],
      "team_keys": [
        "frc2724",
        "frc6500",
        "frc3680"
      ]
    },
    "red": {
      "dq_team_keys": [],
      "score": 267,
      "surrogate_team_keys": [],
      "team_keys": [
        "frc3506",
        "frc8746",
        "frc4534"
      ]
    }
  },
  "comp_level": "f",
  "event_key": "2026nccab",
  "key": "2026nccab_f1m1",
  "match_number": 1,
  "post_result_time": 1773001501,
  "predicted_time": 1773001305,
  "score_breakdown": {
    "blue": {
      "adjustPoints": 0,
      "autoTowerPoints": 0,
      "autoTowerRobot1": "None",
      "autoTowerRobot2": "None",
      "autoTowerRobot3": "None",
      "endGameTowerPoints": 0,
      "endGameTowerRobot1": "None",
      "endGameTowerRobot2": "None",
      "endGameTowerRobot3": "None",
      "energizedAchieved": false,
      "foulPoints": 0,
      "g206Penalty": false,
      "hubScore": {
        "autoCount": 21,
        "autoPoints": 21,
        "endgameCount": 34,
        "endgamePoints": 34,
        "shift1Count": 37,
        "shift1Points": 37,
        "shift2Count": 0,
        "shift2Points": 0,
        "shift3Count": 25,
        "shift3Points": 25,
        "shift4Count": 0,
        "shift4Points": 0,
        "teleopCount": 102,
        "teleopPoints": 102,
        "totalCount": 123,
        "totalPoints": 123,
        "transitionCount": 6,
        "transitionPoints": 6,
        "uncounted": 2
      },
      "majorFoulCount": 0,
      "minorFoulCount": 0,
      "penalties": "None",
      "rp": 0,
      "superchargedAchieved": false,
      "totalAutoPoints": 21,
      "totalPoints": 123,
      "totalTeleopPoints": 102,
      "totalTowerPoints": 0,
      "traversalAchieved": false
    },
    "red": {
      "adjustPoints": 0,
      "autoTowerPoints": 0,
      "autoTowerRobot1": "None",
      "autoTowerRobot2": "None",
      "autoTowerRobot3": "None",
      "endGameTowerPoints": 0,
      "endGameTowerRobot1": "None",
      "endGameTowerRobot2": "None",
      "endGameTowerRobot3": "None",
      "energizedAchieved": false,
      "foulPoints": 0,
      "g206Penalty": false,
      "hubScore": {
        "autoCount": 40,
        "autoPoints": 40,
        "endgameCount": 64,
        "endgamePoints": 64,
        "shift1Count": 0,
        "shift1Points": 0,
        "shift2Count": 92,
        "shift2Points": 92,
        "shift3Count": 0,
        "shift3Points": 0,
        "shift4Count": 62,
        "shift4Points": 62,
        "teleopCount": 227,
        "teleopPoints": 227,
        "totalCount": 267,
        "totalPoints": 267,
        "transitionCount": 9,
        "transitionPoints": 9,
        "uncounted": 1
      },
      "majorFoulCount": 0,
      "minorFoulCount": 0,
      "penalties": "None",
      "rp": 0,
      "superchargedAchieved": false,
      "totalAutoPoints": 40,
      "totalPoints": 267,
      "totalTeleopPoints": 227,
      "totalTowerPoints": 0,
      "traversalAchieved": false
    }
  },
  "set_number": 1,
  "time": 1772999040,
  "videos": [
    {
      "key": "4AmZfS0PgGk",
      "type": "youtube"
    }
  ],
  "winning_alliance": "red"
}